Metadata-Version: 2.1
Name: yaidng
Version: 24.1.0
Summary: Yandex ID oauth API wrapper
Home-page: https://github.com/LulzLoL231/yandexid
License: MIT
Keywords: yandex,oauth,api,wrapper,yandexid,yandex-id
Author: Rick Sanchez
Requires-Python: >=3.10,<4.0
Classifier: Development Status :: 3 - Alpha
Classifier: Intended Audience :: Developers
Classifier: License :: OSI Approved :: MIT License
Classifier: Operating System :: OS Independent
Classifier: Programming Language :: Python :: 3
Classifier: Programming Language :: Python :: 3.10
Classifier: Programming Language :: Python :: 3.11
Classifier: Programming Language :: Python :: 3.12
Classifier: Topic :: Software Development :: Libraries :: Python Modules
Requires-Dist: PyJWT (>=2.6.0,<3.0.0)
Requires-Dist: httpx (>=0.26.0,<0.27.0)
Requires-Dist: pydantic (>=2.6.1,<3.0.0)
Project-URL: Repository, https://github.com/LulzLoL231/yandexid
